airflint/__init__.py
airflint/__main__.py
airflint/actions/new_statements.py
airflint/rules/use_function_level_imports.py
airflint/rules/use_jinja_variable_get.py
airflint-0.3.2a0.dist-info/entry_points.txt
airflint-0.3.2a0.dist-info/LICENSE
airflint-0.3.2a0.dist-info/WHEEL
airflint-0.3.2a0.dist-info/METADATA
airflint-0.3.2a0.dist-info/RECORD
