Metadata-Version: 2.1
Name: airflint
Version: 0.3.2a0
Summary: Enforce Best Practices for all your Airflow DAGs. ⭐
License: Apache-2.0
Keywords: airflow,best-practices,dag
Author: Felix Uellendall
Author-email: feluelle@pm.me
Requires-Python: >=3.9,<4.0
Classifier: License :: OSI Approved :: Apache Software License
Classifier: Programming Language :: Python :: 3
Classifier: Programming Language :: Python :: 3.10
Classifier: Programming Language :: Python :: 3.9
Requires-Dist: refactor (>=0.4.4,<0.5.0)
